{
    "homepage": "http://www.bandisoft.com/bandizip/",
    "license": "Freeware(EULA)",
    "version": "7.33",
    "hash": "e20bd0a77802efe4274fddb7198977af6b0fe01845b4e1776052881b267b1aa5",
    "url": "https://dl.bandisoft.com/bandizip.std/BANDIZIP-SETUP-STD-X64.EXE#/dl.7z",
    "bin": "Bandizip.exe",
    "pre_install": "Rename-Item \"$dir\\Bandizip.x64.exe\" 'Bandizip.exe'",
    "shortcuts": [
        [
            "Bandizip.exe",
            "Bandizip"
        ]
    ],
    "checkver": {
        "url": "https://en.bandisoft.com/bandizip/history/",
        "re": "<font[^>]+>v([\\d.]+)<"
    },
    "autoupdate": {
        "url": "https://dl.bandisoft.com/bandizip.std/BANDIZIP-SETUP-STD-X64.EXE#/dl.7z"
    }
}
